jvspatial/__init__.py
jvspatial/config.py
jvspatial/exceptions.py
jvspatial/version.py
jvspatial/api/__init__.py
jvspatial/api/config.py
jvspatial/api/constants.py
jvspatial/api/context.py
jvspatial/api/exceptions.py
jvspatial/api/lambda_server.py
jvspatial/api/server.py
jvspatial/api/auth/config.py
jvspatial/api/auth/enhanced.py
jvspatial/api/auth/models.py
jvspatial/api/auth/openapi_config.py
jvspatial/api/auth/service.py
jvspatial/api/components/__init__.py
jvspatial/api/components/app_builder.py
jvspatial/api/components/auth_middleware.py
jvspatial/api/components/endpoint_manager.py
jvspatial/api/components/error_handler.py
jvspatial/api/decorators/__init__.py
jvspatial/api/decorators/field.py
jvspatial/api/decorators/route.py
jvspatial/api/decorators/route_config.py
jvspatial/api/endpoints/__init__.py
jvspatial/api/endpoints/factory.py
jvspatial/api/endpoints/metadata.py
jvspatial/api/endpoints/registry.py
jvspatial/api/endpoints/response.py
jvspatial/api/endpoints/router.py
jvspatial/api/integrations/__init__.py
jvspatial/api/integrations/scheduler/__init__.py
jvspatial/api/integrations/scheduler/decorators.py
jvspatial/api/integrations/scheduler/middleware.py
jvspatial/api/integrations/scheduler/models.py
jvspatial/api/integrations/scheduler/scheduler.py
jvspatial/api/integrations/storage/__init__.py
jvspatial/api/integrations/storage/service.py
jvspatial/api/integrations/webhooks/__init__.py
jvspatial/api/integrations/webhooks/decorators.py
jvspatial/api/integrations/webhooks/helpers.py
jvspatial/api/integrations/webhooks/middleware.py
jvspatial/api/integrations/webhooks/models.py
jvspatial/api/integrations/webhooks/utils.py
jvspatial/api/middleware/__init__.py
jvspatial/api/middleware/manager.py
jvspatial/api/services/__init__.py
jvspatial/api/services/discovery.py
jvspatial/api/services/lifecycle.py
jvspatial/async_utils/__init__.py
jvspatial/cache/__init__.py
jvspatial/cache/base.py
jvspatial/cache/factory.py
jvspatial/cache/layered.py
jvspatial-0.0.2.dist-info/licenses/LICENSE
jvspatial-0.0.2.dist-info/METADATA
jvspatial-0.0.2.dist-info/WHEEL
jvspatial-0.0.2.dist-info/top_level.txt
jvspatial-0.0.2.dist-info/RECORD
