Metadata-Version: 2.4
Name: jvspatial
Version: 0.0.2
Summary: An asynchronous object-spatial Python library for persistence and business logic application layers.
Home-page: https://github.com/trueselph/jvspatial
Author: TrueSelph Inc.
Author-email: "TrueSelph Inc." <adminh@trueselph.com>
License: MIT
Project-URL: Homepage, https://github.com/TrueSelph/jvspatial
Project-URL: Repository, https://github.com/TrueSelph/jvspatial
Project-URL: Issues, https://github.com/TrueSelph/jvspatial/issues
Project-URL: Documentation, https://github.com/TrueSelph/jvspatial/tree/main/docs
Keywords: async,graph,spatial,persistence,business-logic
Classifier: Development Status :: 4 - Beta
Classifier: Intended Audience :: Developers
Classifier: License :: OSI Approved :: MIT License
Classifier: Programming Language :: Python :: 3.8
Classifier: Programming Language :: Python :: 3.9
Classifier: Programming Language :: Python :: 3.10
Classifier: Programming Language :: Python :: 3.11
Classifier: Programming Language :: Python :: 3.12
Classifier: Framework :: FastAPI
Classifier: Topic :: Database
Classifier: Topic :: Software Development :: Libraries :: Python Modules
Requires-Python: >=3.8
License-File: LICENSE
Requires-Dist: pydantic>=2.0
Requires-Dist: fastapi>=0.100.0
Requires-Dist: uvicorn>=0.23.0
Requires-Dist: python-multipart>=0.0.6
Requires-Dist: motor>=3.0.0
Requires-Dist: pymongo>=4.0.0
Requires-Dist: PyJWT>=2.0.0
Requires-Dist: bcrypt>=4.0.0
Requires-Dist: schedule>=1.2.2
Requires-Dist: typing-extensions>=4.0.0
Requires-Dist: aiosqlite>=0.19.0
Provides-Extra: dev
Requires-Dist: pytest>=7.0; extra == "dev"
Requires-Dist: pytest-asyncio>=0.21.0; extra == "dev"
Requires-Dist: httpx>=0.24.0; extra == "dev"
Requires-Dist: pre-commit>=3.0.0; extra == "dev"
Requires-Dist: python-dotenv>=1.0.0; extra == "dev"
Provides-Extra: test
Requires-Dist: pytest>=7.0; extra == "test"
Requires-Dist: pytest-asyncio>=0.21.0; extra == "test"
Requires-Dist: httpx>=0.24.0; extra == "test"
Provides-Extra: scheduler
Requires-Dist: psutil>=5.9.0; extra == "scheduler"
Requires-Dist: python-dotenv>=1.0.0; extra == "scheduler"
Provides-Extra: serverless
Requires-Dist: mangum>=0.17.0; extra == "serverless"
Requires-Dist: aioboto3>=12.0.0; extra == "serverless"
Provides-Extra: all
Requires-Dist: pytest>=7.0; extra == "all"
Requires-Dist: pytest-asyncio>=0.21.0; extra == "all"
Requires-Dist: httpx>=0.24.0; extra == "all"
Requires-Dist: pre-commit>=3.0.0; extra == "all"
Requires-Dist: python-dotenv>=1.0.0; extra == "all"
Requires-Dist: psutil>=5.9.0; extra == "all"
Requires-Dist: mangum>=0.17.0; extra == "all"
Requires-Dist: aioboto3>=12.0.0; extra == "all"
Dynamic: author
Dynamic: home-page
Dynamic: license-file
Dynamic: requires-python
